cobra_component_models/__init__.py
cobra_component_models/_version.py
cobra_component_models/helpers.py
cobra_component_models/builder/__init__.py
cobra_component_models/builder/abstract_builder.py
cobra_component_models/builder/compartment_builder.py
cobra_component_models/builder/compound_builder.py
cobra_component_models/builder/reaction_builder.py
cobra_component_models/io/__init__.py
cobra_component_models/io/abstract_base_model.py
cobra_component_models/io/annotation_model.py
cobra_component_models/io/compartment_model.py
cobra_component_models/io/components_model.py
cobra_component_models/io/compound_model.py
cobra_component_models/io/io_base.py
cobra_component_models/io/name_model.py
cobra_component_models/io/reaction_model.py
cobra_component_models/io/type/__init__.py
cobra_component_models/io/type/notes_type.py
cobra_component_models/orm/__init__.py
cobra_component_models/orm/abstract_component.py
cobra_component_models/orm/base.py
cobra_component_models/orm/compartment.py
cobra_component_models/orm/compartment_annotation.py
cobra_component_models/orm/compartment_name.py
cobra_component_models/orm/compound.py
cobra_component_models/orm/compound_annotation.py
cobra_component_models/orm/compound_name.py
cobra_component_models/orm/namespace.py
cobra_component_models/orm/participant.py
cobra_component_models/orm/reaction.py
cobra_component_models/orm/reaction_annotation.py
cobra_component_models/orm/reaction_name.py
cobra_component_models/orm/mixin/__init__.py
cobra_component_models/orm/mixin/annotation_mixin.py
cobra_component_models/orm/mixin/name_mixin.py
cobra_component_models/orm/mixin/timestamp_mixin.py
cobra_component_models-0.6.0.dist-info/LICENSE
cobra_component_models-0.6.0.dist-info/METADATA
cobra_component_models-0.6.0.dist-info/WHEEL
cobra_component_models-0.6.0.dist-info/top_level.txt
cobra_component_models-0.6.0.dist-info/zip-safe
cobra_component_models-0.6.0.dist-info/RECORD
