Metadata-Version: 2.1
Name: cobra-component-models
Version: 0.6.0
Summary: SQLAlchemy ORM and pydantic data models for SQL storage and JSON serialization of COBRA components such as reactions, compounds, and compartments.
Home-page: https://github.com/opencobra/cobra-component-models
Author: Moritz E. Beber
Author-email: midnighter@posteo.net
License: Apache-2.0
Download-URL: https://pypi.org/project/cobra-component-models/
Project-URL: Source Code, https://github.com/opencobra/cobra-component-models
Project-URL: Documentation, https://cobra-component-models.readthedocs.io
Project-URL: Bug Tracker, https://github.com/opencobra/cobra-component-models/issues
Keywords: COBRA,data models,ORM models
Platform: UNKNOWN
Classifier: Development Status :: 2 - Pre-Alpha
Classifier: Intended Audience :: Science/Research
Classifier: License :: OSI Approved :: Apache Software License
Classifier: License :: OSI Approved :: MIT License
Classifier: Natural Language :: English
Classifier: Operating System :: OS Independent
Classifier: Programming Language :: Python :: 3 :: Only
Classifier: Programming Language :: Python :: 3.7
Classifier: Programming Language :: Python :: 3.8
Classifier: Programming Language :: Python :: 3.9
Classifier: Topic :: Scientific/Engineering :: Bio-Informatics
Requires-Python: >=3.7
License-File: LICENSE
Requires-Dist: depinfo (~=1.5)
Requires-Dist: pydantic (~=1.4)
Requires-Dist: SQLAlchemy (~=1.3)
Provides-Extra: development
Requires-Dist: black ; extra == 'development'
Requires-Dist: isort ; extra == 'development'
Requires-Dist: pep517 ; extra == 'development'
Requires-Dist: tox ; extra == 'development'
